apricot/__init__.py
apricot/optimizers.py
apricot/utils.py
apricot/functions/__init__.py
apricot/functions/base.py
apricot/functions/custom.py
apricot/functions/facilityLocation.py
apricot/functions/featureBased.py
apricot/functions/graphCut.py
apricot/functions/maxCoverage.py
apricot/functions/maxRedundancy.py
apricot/functions/maximumCoverage.py
apricot/functions/mixture.py
apricot/functions/saturatedCoverage.py
apricot/functions/sumRedundancy.py
apricot_select-0.6.0.dist-info/LICENSE
apricot_select-0.6.0.dist-info/METADATA
apricot_select-0.6.0.dist-info/WHEEL
apricot_select-0.6.0.dist-info/top_level.txt
apricot_select-0.6.0.dist-info/RECORD
