Metadata-Version: 2.1
Name: apricot-select
Version: 0.6.0
Summary: apricot is a package for submodular selection of representative sets for machine learning models.
Home-page: http://pypi.python.org/pypi/apricot-select/
Author: Jacob Schreiber
Author-email: jmschreiber91@gmail.com
License: LICENSE.txt
Platform: UNKNOWN
Requires-Dist: numpy (>=1.14.2)
Requires-Dist: scipy (>=1.0.0)
Requires-Dist: numba (>=0.43.0)
Requires-Dist: tqdm (>=4.24.0)
Requires-Dist: nose
